{
  "version": "0.1",
  "generated_at": "2026-03-21",
  "namespace": "awareness",
  "cards": [
    {
      "id": "IC01",
      "slug": "fujin-raijin-screen",
      "image": "image-cards/items/fujin-raijin-screen.jpg",
      "title_ja": "風神雷神図",
      "title_en": "Fujin-Raijin Screen",
      "comment_ja": "二つの力が対立ではなく緊張した共存として置かれていることを読むための観察カード。意識モデルでは、単純な善悪の分割ではなく複数の向きが同時に立ち上がる場面の比喩として扱える。",
      "comment_en": "An observation card for reading the image as tense coexistence rather than simple opposition. In the awareness model, it can serve as a metaphor for moments in which multiple directions rise at once rather than splitting into good and evil.",
      "alt_ja": "俵屋宗達の風神雷神図屏風",
      "alt_en": "Sotatsu Tawaraya's Fujin-Raijin folding screen",
      "source_url": "https://uminomae.github.io/pjdhiro/assets/images/humor/Fujinraijin-tawarayaCom.avif.jpg",
      "generated": "2026-03-21",
      "generator_model": "not_applicable",
      "sort_order": 10
    },
    {
      "id": "IC02",
      "slug": "intent",
      "image": "image-cards/items/intent.jpg",
      "title_ja": "意",
      "title_en": "Intent",
      "comment_ja": "身体の揺らぎからゲート、意、意味生成、価値整形、決定、思へ至る流れを一枚で図解した画像です。",
      "comment_en": "A diagram that maps the flow from bodily fluctuation through gate, intent, meaning generation, value shaping, decision, and thought in a single image.",
      "alt_ja": "身体から思までの処理連鎖を段階的に示した模式図",
      "alt_en": "A schematic diagram showing the processing chain from body to thought in staged steps",
      "source_url": "",
      "generated": "2026-03-21",
      "generator_model": "codex:auto-ingest",
      "sort_order": 9007199254740991
    },
    {
      "id": "IC03",
      "slug": "intent-gorilla",
      "image": "image-cards/items/intent-gorilla.jpg",
      "title_ja": "Intent Gorilla",
      "title_en": "Intent Gorilla",
      "comment_ja": "Intent Gorilla をテーマにした追加画像です。画像カードとして自動取り込みしています。",
      "comment_en": "An additional image card centered on Intent Gorilla. It was imported automatically into the image-card collection.",
      "alt_ja": "Intent Gorilla",
      "alt_en": "Intent Gorilla",
      "source_url": "",
      "generated": "2026-03-21",
      "generator_model": "codex:auto-ingest",
      "sort_order": 9007199254740991
    },
    {
      "id": "IC04",
      "slug": "intent-love",
      "image": "image-cards/items/intent-love.jpg",
      "title_ja": "Intent Love",
      "title_en": "Intent Love",
      "comment_ja": "Intent Love をテーマにした追加画像です。画像カードとして自動取り込みしています。",
      "comment_en": "An additional image card centered on Intent Love. It was imported automatically into the image-card collection.",
      "alt_ja": "Intent Love",
      "alt_en": "Intent Love",
      "source_url": "",
      "generated": "2026-03-21",
      "generator_model": "codex:auto-ingest",
      "sort_order": 9007199254740991
    },
    {
      "id": "IC05",
      "slug": "intent-org",
      "image": "image-cards/items/intent-org.jpg",
      "title_ja": "Intent Org",
      "title_en": "Intent Org",
      "comment_ja": "Intent Org をテーマにした追加画像です。画像カードとして自動取り込みしています。",
      "comment_en": "An additional image card centered on Intent Org. It was imported automatically into the image-card collection.",
      "alt_ja": "Intent Org",
      "alt_en": "Intent Org",
      "source_url": "",
      "generated": "2026-03-21",
      "generator_model": "codex:auto-ingest",
      "sort_order": 9007199254740991
    },
    {
      "id": "IC06",
      "slug": "intent2",
      "image": "image-cards/items/intent2.jpg",
      "title_ja": "Intent2",
      "title_en": "Intent2",
      "comment_ja": "Intent2 をテーマにした追加画像です。画像カードとして自動取り込みしています。",
      "comment_en": "An additional image card centered on Intent2. It was imported automatically into the image-card collection.",
      "alt_ja": "Intent2",
      "alt_en": "Intent2",
      "source_url": "",
      "generated": "2026-03-21",
      "generator_model": "codex:auto-ingest",
      "sort_order": 9007199254740991
    }
  ]
}
